mvtpy/__init__.py
mvtpy/mvtest.py
mvtpy-0.15.dist-info/METADATA
mvtpy-0.15.dist-info/WHEEL
mvtpy-0.15.dist-info/top_level.txt
mvtpy-0.15.dist-info/RECORD
