Metadata-Version: 2.1
Name: mvtpy
Version: 0.15
Summary: A Distribution-Free Test of Independence Based on Mean Variance Index.
Home-page: https://github.com/ChuanyuXue/MVTest
Author: Chuanyu Xue
Author-email: cs_xcy@126.com
Maintainer: Chuanyu Xue
Maintainer-email: cs_xcy@126.com
License: BSD License
Platform: all
Requires-Dist: NumPy (>=1.12.0)
